catastrophe/__init__.py
catastrophe/__main__.py
catastrophe/affine.py
catastrophe/atbash.py
catastrophe/auto.py
catastrophe/autoguess.py
catastrophe/autokey.py
catastrophe/baconian.py
catastrophe/base64c.py
catastrophe/beaufort.py
catastrophe/bruteforce.py
catastrophe/caesar.py
catastrophe/classifier.py
catastrophe/columnar.py
catastrophe/columnarv2.py
catastrophe/enigma.py
catastrophe/entropy.py
catastrophe/frequency.py
catastrophe/hill.py
catastrophe/homophonic.py
catastrophe/install.py
catastrophe/keyword.py
catastrophe/langdetect.py
catastrophe/language.py
catastrophe/morse.py
catastrophe/ngrams.py
catastrophe/playfair.py
catastrophe/polyalphabetic.py
catastrophe/polybius.py
catastrophe/porta.py
catastrophe/railfence.py
catastrophe/rot13.py
catastrophe/rot47.py
catastrophe/sandbox.py
catastrophe/scorer.py
catastrophe/scytale.py
catastrophe/scytale_double.py
catastrophe/skanthem.py
catastrophe/sponsorship.py
catastrophe/tester.py
catastrophe/translit_maps.py
catastrophe/transliterate.py
catastrophe/uninstaller.py
catastrophe/updater.py
catastrophe/vigenere.py
catastrophe/wordscore.py
catastrophe/xor.py
catastrophe/yarr.py
catastrophe-0.1.15.dist-info/licenses/LICENSE
catastrophe-0.1.15.dist-info/METADATA
catastrophe-0.1.15.dist-info/WHEEL
catastrophe-0.1.15.dist-info/entry_points.txt
catastrophe-0.1.15.dist-info/top_level.txt
catastrophe-0.1.15.dist-info/RECORD
