Metadata-Version: 2.4
Name: catastrophe
Version: 0.1.15
Summary: A sandbox-style cryptography and classical cipher toolkit.
Author: burning-calamity
License-Expression: MIT
Keywords: cipher,cryptography,encryption,sandbox
Classifier: Programming Language :: Python :: 3
Classifier: Operating System :: OS Independent
Requires-Python: >=3.8
License-File: LICENSE
Dynamic: license-file
